cupyopt/__init__.py
cupyopt/objectstore_tasks.py
cupyopt/oradb_tasks.py
cupyopt/sftp_tasks.py
cupyopt/task_factory.py
cupyopt/nuggets/__init__.py
cupyopt/nuggets/dataframe.py
cupyopt/nuggets/schema.py
cupyopt/nuggets/validation.py
cupyopt-0.15.13.2.dist-info/LICENSE
cupyopt-0.15.13.2.dist-info/METADATA
cupyopt-0.15.13.2.dist-info/WHEEL
cupyopt-0.15.13.2.dist-info/top_level.txt
cupyopt-0.15.13.2.dist-info/RECORD
