Metadata-Version: 2.1
Name: cupyopt
Version: 0.15.13.2
Summary: CU Python Opinionated Prefect Tasks
Home-page: UNKNOWN
Author: CU Boulder, OIT
Author-email: stta9820@colorado.edu
License: Apache License 2.0
Platform: UNKNOWN
Classifier: License :: OSI Approved :: Apache Software License
Classifier: Operating System :: OS Independent
Requires-Python: >=3.6
Requires-Dist: bandit
Requires-Dist: black
Requires-Dist: cx-Oracle
Requires-Dist: fastavro (==1.0.0.post1)
Requires-Dist: minio
Requires-Dist: nose
Requires-Dist: pandas
Requires-Dist: pandavro (==1.6.0)
Requires-Dist: prefect (==0.15.13)
Requires-Dist: pyarrow (==6.0.1)
Requires-Dist: pygrok
Requires-Dist: pylint
Requires-Dist: pysftp
Requires-Dist: pytest
Requires-Dist: sqlalchemy
Requires-Dist: typing-extensions
Requires-Dist: yamllint
